autumn8/__init__.py
autumn8/exceptions.py
autumn8/i18n.py
autumn8/libenv.py
autumn8/cli/__init__.py
autumn8/cli/__main__.py
autumn8/cli/analyze.py
autumn8/cli/cli_environment.py
autumn8/cli/examples.py
autumn8/cli/interactive.py
autumn8/cli/main.py
autumn8/cli/options.py
autumn8/cli/pending_uploads.py
autumn8/cli/validation.py
autumn8/cli/commands/cloud.py
autumn8/cli/commands/models.py
autumn8/common/__init__.py
autumn8/common/_version.py
autumn8/common/types.py
autumn8/common/config/__init__.py
autumn8/common/config/cloud_info.py
autumn8/common/config/settings.py
autumn8/common/config/supported_instances.py
autumn8/env/__init__.py
autumn8/env/app.py
autumn8/env/cli.py
autumn8/env/predictor.py
autumn8/env/worker.py
autumn8/examples/convblock.py
autumn8/examples/loadMnist.py
autumn8/examples/mnist.py
autumn8/examples/model.py
autumn8/examples/sbert-alpha.py
autumn8/examples/tensorflow_custom_layers.py
autumn8/examples/whisper.py
autumn8/lib/__init__.py
autumn8/lib/api_creds.py
autumn8/lib/asyncio.py
autumn8/lib/http.py
autumn8/lib/logging.py
autumn8/lib/logging.yaml
autumn8/lib/package_resolver.py
autumn8/lib/pydantic.py
autumn8/lib/service.py
autumn8/lib/api/__init__.py
autumn8/lib/api/cloud.py
autumn8/lib/api/lab.py
autumn8/lib/api/user.py
autumn8/types/deployment.py
autumn8/types/router.py
autumn8-2.0.8.dist-info/METADATA
autumn8-2.0.8.dist-info/WHEEL
autumn8-2.0.8.dist-info/entry_points.txt
autumn8-2.0.8.dist-info/top_level.txt
autumn8-2.0.8.dist-info/RECORD
