Metadata-Version: 2.1
Name: autumn8
Version: 2.0.8
Summary: Utilities to export models to the autumn8.ai service
Author-email: Autumn8 <team@autumn8.ai>
Requires-Python: >=3.8
Requires-Dist: appdirs
Requires-Dist: wheel >=0.31.0
Requires-Dist: boto3 >=1.20.15
Requires-Dist: click >=8.0.1
Requires-Dist: questionary >=1.10.0
Requires-Dist: tqdm
Requires-Dist: fastapi
Requires-Dist: pyyaml
Requires-Dist: jsonschema
Requires-Dist: requests
Requires-Dist: httpx
Requires-Dist: boto3-stubs[s3,sts]
